WithSecure/__init__.py
WithSecure/common/__init__.py
WithSecure/common/argparse_completer.py
WithSecure/common/cli.py
WithSecure/common/cmd_ext.py
WithSecure/common/command_wrapper.py
WithSecure/common/console.py
WithSecure/common/fs.py
WithSecure/common/list.py
WithSecure/common/logger.py
WithSecure/common/path_completion.py
WithSecure/common/stream.py
WithSecure/common/system.py
WithSecure/common/text.py
WithSecure/common/twisted/__init__.py
WithSecure/common/twisted/stream_receiver.py
drozer/__init__.py
drozer/android.py
drozer/autocomplete.py
drozer/configuration.py
drozer/device.py
drozer/main.py
drozer/meta.py
drozer/session.py
drozer/util.py
drozer/agent/__init__.py
drozer/agent/builder.py
drozer/agent/manager.py
drozer/agent/manifest.py
drozer/api/__init__.py
drozer/api/formatters/__init__.py
drozer/api/formatters/system_response.py
drozer/api/handlers/__init__.py
drozer/api/handlers/reflection_request_forwarder.py
drozer/api/handlers/reflection_response_forwarder.py
drozer/api/handlers/system_request_handler.py
drozer/api/handlers/system_response_handler.py
drozer/cli/__init__.py
drozer/cli/agent.py
drozer/cli/console.py
drozer/cli/exploit.py
drozer/cli/module.py
drozer/cli/payload.py
drozer/cli/server.py
drozer/cli/ssl.py
drozer/connector/__init__.py
drozer/connector/server_connector.py
drozer/console/__init__.py
drozer/console/clean.py
drozer/console/console.py
drozer/console/sequencer.py
drozer/console/session.py
drozer/exploit/__init__.py
drozer/exploit/builder.py
drozer/exploit/manager.py
drozer/lib/aapt
drozer/lib/aapt-osx
drozer/lib/aapt.exe
drozer/lib/agent.jar
drozer/lib/android-support-v4.jar
drozer/lib/android.jar
drozer/lib/apktool.jar
drozer/lib/certificate.pem
drozer/lib/d8
drozer/lib/d8.bat
drozer/lib/d8.jar
drozer/lib/find_java.bat
drozer/lib/find_java.exe
drozer/lib/key.pk8
drozer/lib/protobuf-java-3.22.2.jar
drozer/lib/signapk.jar
drozer/lib/WebViewContext/jni/Android.mk
drozer/lib/WebViewContext/jni/Application.mk
drozer-3.1.0.dist-info/LICENSE
drozer-3.1.0.dist-info/METADATA
drozer-3.1.0.dist-info/WHEEL
drozer-3.1.0.dist-info/entry_points.txt
drozer-3.1.0.dist-info/top_level.txt
drozer-3.1.0.dist-info/RECORD
