Metadata-Version: 2.1
Name: drozer
Version: 3.1.0
Summary: The Leading Android Security Testing Framework
Author-email: WithSecure <drozer@withsecure.com>
License: BSD 3-Clause License
Project-URL: Homepage, https://labs.withsecure.com/tools/drozer/
Project-URL: Documentation, https://labs.withsecure.com/tools/drozer/
Project-URL: Repository, https://github.com/WithSecureLabs/drozer.git
Project-URL: Issues, https://github.com/WithSecureLabs/drozer/issues
Keywords: drozer,android,security,framework
Classifier: Programming Language :: Python :: 3
Classifier: License :: OSI Approved :: BSD License
Classifier: Operating System :: OS Independent
Classifier: Topic :: Security
Requires-Python: >=3.8
License-File: LICENSE
Requires-Dist: protobuf >=4.25.2
Requires-Dist: pyopenssl >=22.0.0
Requires-Dist: twisted >=18.9.0
Requires-Dist: service-identity
Requires-Dist: distro
Requires-Dist: pyyaml
